stageflow/__init__.py
stageflow/extensions.py
stageflow/protocols.py
stageflow/py.typed
stageflow/testing.py
stageflow/agent/__init__.py
stageflow/auth/__init__.py
stageflow/auth/context.py
stageflow/auth/errors.py
stageflow/auth/events.py
stageflow/auth/interceptors.py
stageflow/auth/tenant.py
stageflow/cli/__init__.py
stageflow/cli/__main__.py
stageflow/cli/lint.py
stageflow/compression/__init__.py
stageflow/context/__init__.py
stageflow/context/bag.py
stageflow/context/context_snapshot.py
stageflow/context/conversation.py
stageflow/context/enrich.py
stageflow/context/enrichments.py
stageflow/context/extensions.py
stageflow/context/identity.py
stageflow/context/output_bag.py
stageflow/context/types.py
stageflow/contracts/__init__.py
stageflow/contracts/errors.py
stageflow/contracts/registry.py
stageflow/contracts/suggestions.py
stageflow/contracts/typed_output.py
stageflow/core/__init__.py
stageflow/core/stage_context.py
stageflow/core/stage_enums.py
stageflow/core/stage_output.py
stageflow/core/stage_protocol.py
stageflow/core/timer.py
stageflow/events/__init__.py
stageflow/events/sink.py
stageflow/helpers/__init__.py
stageflow/helpers/analytics.py
stageflow/helpers/guardrails.py
stageflow/helpers/memory.py
stageflow/helpers/memory_tracker.py
stageflow/helpers/mocks.py
stageflow/helpers/providers.py
stageflow/helpers/run_utils.py
stageflow/helpers/streaming.py
stageflow/helpers/timestamps.py
stageflow/helpers/uuid_utils.py
stageflow/observability/__init__.py
stageflow/observability/tracing.py
stageflow/observability/wide_events.py
stageflow/pipeline/__init__.py
stageflow/pipeline/builder.py
stageflow/pipeline/builder_helpers.py
stageflow/pipeline/cancellation.py
stageflow/pipeline/dag.py
stageflow/pipeline/failure_tolerance.py
stageflow/pipeline/guard_retry.py
stageflow/pipeline/idempotency.py
stageflow/pipeline/interceptors.py
stageflow/pipeline/interceptors_hardening.py
stageflow/pipeline/interfaces.py
stageflow/pipeline/pipeline.py
stageflow_core-0.9.1.dist-info/METADATA
stageflow_core-0.9.1.dist-info/WHEEL
stageflow_core-0.9.1.dist-info/RECORD
