Metadata-Version: 2.4
Name: stageflow-core
Version: 0.9.1
Summary: A DAG-based pipeline orchestration framework for building observable, composable stage pipelines
Project-URL: Homepage, https://github.com/stageflow/stageflow
Project-URL: Documentation, https://github.com/stageflow/stageflow#readme
Project-URL: Repository, https://github.com/stageflow/stageflow
Author: Stageflow Contributors
License-Expression: MIT
Keywords: async,dag,observability,orchestration,pipeline,stages,workflow
Classifier: Development Status :: 4 - Beta
Classifier: Framework :: AsyncIO
Classifier: Intended Audience :: Developers
Classifier: License :: OSI Approved :: MIT License
Classifier: Programming Language :: Python :: 3
Classifier: Programming Language :: Python :: 3.11
Classifier: Programming Language :: Python :: 3.12
Classifier: Programming Language :: Python :: 3.13
Classifier: Topic :: Software Development :: Libraries :: Python Modules
Classifier: Typing :: Typed
Requires-Python: >=3.11
Requires-Dist: pydantic<3.0,>=2.0
Requires-Dist: uuid6>=2024.1.12
Provides-Extra: dev
Requires-Dist: hypothesis>=6.0; extra == 'dev'
Requires-Dist: mypy>=1.8; extra == 'dev'
Requires-Dist: pytest-asyncio>=0.23; extra == 'dev'
Requires-Dist: pytest-benchmark>=4.0; extra == 'dev'
Requires-Dist: pytest-cov>=4.0; extra == 'dev'
Requires-Dist: pytest>=8.0; extra == 'dev'
Requires-Dist: ruff>=0.1; extra == 'dev'
Provides-Extra: websearch
Requires-Dist: httpx>=0.25; extra == 'websearch'
Requires-Dist: selectolax>=0.3; extra == 'websearch'
